cpp_code_style_formatter/WorkingMode.py
cpp_code_style_formatter/__init__.py
cpp_code_style_formatter/__main__.py
cpp_code_style_formatter/automaton.py
cpp_code_style_formatter/code_style_checker.py
cpp_code_style_formatter/code_style_checker_runner.py
cpp_code_style_formatter/finite_state_machine.py
cpp_code_style_formatter/lexer.py
cpp_code_style_formatter/logger.py
cpp_code_style_formatter/name_formatter.py
cpp_code_style_formatter/patterns.py
cpp_code_style_formatter/state.py
cpp_code_style_formatter/state_machine_factory.py
cpp_code_style_formatter/token.py
cpp_code_style_formatter/transition.py
cpp_code_style_formatter-1.0.4.dist-info/METADATA
cpp_code_style_formatter-1.0.4.dist-info/WHEEL
cpp_code_style_formatter-1.0.4.dist-info/entry_points.txt
cpp_code_style_formatter-1.0.4.dist-info/top_level.txt
cpp_code_style_formatter-1.0.4.dist-info/RECORD
