Metadata-Version: 2.1
Name: cpp-code-style-formatter
Version: 1.0.4
Summary: Formatter cam format cpp code(cpp_code_style_formatter --format -f <path to file>)
Home-page: UNKNOWN
Author: Stanislav Dzundza
Author-email: stas.dzundza@gmail.com
License: UNKNOWN
Platform: UNKNOWN
